pyftdi/INSTALL
pyftdi/__init__.py
pyftdi/bits.py
pyftdi/d2xx.py
pyftdi/eeprom.py
pyftdi/ftdi.py
pyftdi/gpio.py
pyftdi/i2c.py
pyftdi/jtag.py
pyftdi/misc.py
pyftdi/spi.py
pyftdi/term.py
pyftdi/tracer.py
pyftdi/usbtools.py
pyftdi/doc/authors.rst
pyftdi/doc/defs.rst
pyftdi/doc/eeprom.rst
pyftdi/doc/features.rst
pyftdi/doc/gpio.rst
pyftdi/doc/index.rst
pyftdi/doc/installation.rst
pyftdi/doc/license.rst
pyftdi/doc/pinout.rst
pyftdi/doc/requirements.rst
pyftdi/doc/testing.rst
pyftdi/doc/tools.rst
pyftdi/doc/troubleshooting.rst
pyftdi/doc/urlscheme.rst
pyftdi/doc/api/eeprom.rst
pyftdi/doc/api/ftdi.rst
pyftdi/doc/api/gpio.rst
pyftdi/doc/api/i2c.rst
pyftdi/doc/api/index.rst
pyftdi/doc/api/misc.rst
pyftdi/doc/api/spi.rst
pyftdi/doc/api/uart.rst
pyftdi/doc/api/usbtools.rst
pyftdi/serialext/__init__.py
pyftdi/serialext/logger.py
pyftdi/serialext/protocol_ftdi.py
pyftdi/serialext/protocol_unix.py
pyftdiwin-0.54.1.dist-info/METADATA
pyftdiwin-0.54.1.dist-info/WHEEL
pyftdiwin-0.54.1.dist-info/entry_points.txt
pyftdiwin-0.54.1.dist-info/license.rst
pyftdiwin-0.54.1.dist-info/top_level.txt
pyftdiwin-0.54.1.dist-info/RECORD
