Metadata-Version: 2.1
Name: pyftdiwin
Version: 0.54.1
Summary: Python FTDI library for Windows
Home-page: https://github.com/mariusgreuel/pyftdiwin
Author: Marius Greuel
Author-email: greuelm@mgtek.com
Maintainer: Marius Greuel
Maintainer-email: greuelm@mgtek.com
License: Modified BSD
Keywords: driver,ftdi,usb,serial,spi,i2c,twi,rs232,gpio,bit-bang
Classifier: Development Status :: 4 - Beta
Classifier: Environment :: Other Environment
Classifier: Natural Language :: English
Classifier: Intended Audience :: Developers
Classifier: License :: OSI Approved :: BSD License
Classifier: Operating System :: MacOS :: MacOS X
Classifier: Operating System :: POSIX
Classifier: Operating System :: Microsoft :: Windows
Classifier: Programming Language :: Python :: 3.7
Classifier: Programming Language :: Python :: 3.8
Classifier: Programming Language :: Python :: 3.9
Classifier: Programming Language :: Python :: 3.10
Classifier: Topic :: Software Development :: Libraries :: Python Modules
Classifier: Topic :: System :: Hardware :: Hardware Drivers
Requires-Python: >=3.7
License-File: pyftdi/doc/license.rst
Requires-Dist: pyusb (!=1.2.0,>=1.0.0)
Requires-Dist: pyserial (>=3.0)
